[
  {
    "type": "speech",
    "speaker": [ "FoxmonImperialReaper" ],
    "sound": "\"Things are looking pretty grim.\"",
    "volume": 40
  },
  {
    "type": "speech",
    "speaker": [ "FoxmonImperialReaper" ],
    "sound": "\"Where the hell is everyone?\"",
    "volume": 40
  },
  {
    "type": "speech",
    "speaker": [ "FoxmonImperialReaper" ],
    "sound": "\"I miss the trenches.\"",
    "volume": 40
  },
  {
    "type": "speech",
    "speaker": [ "FoxmonImperialReaper" ],
    "sound": "\"How long until we starve?\"",
    "volume": 40
  },
  {
    "type": "speech",
    "speaker": [ "FoxmonImperialReaper" ],
    "sound": "\"How did I get here?\"",
    "volume": 40
  },
  {
    "type": "speech",
    "speaker": [ "FoxmonImperialReaper" ],
    "sound": "\"Where the hell are we?\"",
    "volume": 40
  },
  {
    "type": "speech",
    "speaker": [ "FoxmonImperialReaper" ],
    "sound": "\"How do acorns taste worse than our slop?\"",
    "volume": 40
  },
  {
    "type": "speech",
    "speaker": [ "FoxmonImperialReaper" ],
    "sound": "\"I'll be home soon, just remember me.\"",
    "volume": 40
  },
  {
    "type": "speech",
    "speaker": [ "FoxmonImperialReaper" ],
    "sound": "\"Half of us didn't make it. They vomitted blood, some had their insides end up outside.\"",
    "volume": 40
  },
  {
    "type": "speech",
    "speaker": [ "FoxmonImperialReaper" ],
    "sound": "\"I didn't check what hit the car, I ran for the treeline and saw it ablaze.\"",
    "volume": 40
  },
  {
    "type": "speech",
    "speaker": [ "FoxmonImperialReaper" ],
    "sound": "\"A rocket hit the front, took out our driver and navigator. Engine was no good.\"",
    "volume": 40
  },
  {
    "type": "speech",
    "speaker": [ "FoxmonImperialReaper" ],
    "sound": "\"We took fire on arrival, someone followed us here.\"",
    "volume": 40
  },
  {
    "type": "speech",
    "speaker": [ "FoxmonImperialReaper" ],
    "sound": "\"They fucking knew we were coming.\"",
    "volume": 40
  },
  {
    "type": "speech",
    "speaker": [ "FoxmonImperialReaper" ],
    "sound": "\"The books were right, how did we survive these monsters the first time?\"",
    "volume": 40
  },
  {
    "type": "speech",
    "speaker": [ "FoxmonImperialReaper" ],
    "sound": "\"I hope nobody was still alive in the homes we burnt.\"",
    "volume": 40
  },
  {
    "type": "speech",
    "speaker": [ "FoxmonImperialReaper" ],
    "sound": "\"Who the hell are these people? How did they follow us?\"",
    "volume": 40
  },
  {
    "type": "speech",
    "speaker": [ "FoxmonImperialReaper" ],
    "sound": "\"The whole operation went FUBAR after our radio man met a shadow monster.\"",
    "volume": 40
  },
  {
    "type": "speech",
    "speaker": [ "FoxmonImperialReaper" ],
    "sound": "\"He just exploded, how the fuck would I know what happened?\"",
    "volume": 40
  },
  {
    "type": "speech",
    "speaker": [ "FoxmonImperialReaper" ],
    "sound": "\"We found the bodies in the morning amongst the rocks.\"",
    "volume": 40
  },
  {
    "type": "speech",
    "speaker": [ "FoxmonImperialReaper" ],
    "sound": "\"...We kept silent after that.\"",
    "volume": 40
  },
  {
    "type": "speech",
    "speaker": [ "FoxmonImperialReaper" ],
    "sound": "\"To hell with this war.\"",
    "volume": 40
  },
  {
    "type": "speech",
    "speaker": [ "FoxmonImperialReaper" ],
    "sound": "\"So lets drink to those guys who gave their lives for the happiness of others.\"",
    "volume": 40
  },
  {
    "type": "speech",
    "speaker": [ "FoxmonImperialReaper" ],
    "sound": "\"...For those we left laying in the ground.\"",
    "volume": 40
  },
  {
    "type": "speech",
    "speaker": [ "FoxmonImperialReaper" ],
    "sound": "\"Two more months. Just two more months.\"",
    "volume": 40
  },
  {
    "type": "speech",
    "speaker": [ "FoxmonImperialReaper" ],
    "sound": "\"...The radio got knocked out by a lightning bolt last storm.\"",
    "volume": 40
  },
  {
    "type": "speech",
    "speaker": [ "FoxmonImperialReaper" ],
    "sound": "\"I think I saw Her the other day. Maybe the bounty is still good.\"",
    "volume": 40
  },
  {
    "type": "speech",
    "speaker": [ "FoxmonImperialReaper" ],
    "sound": "\"...Then the captain went mad, heading for the treeline.\"",
    "volume": 40
  },
  {
    "type": "speech",
    "speaker": [ "FoxmonImperialReaper" ],
    "sound": "\"We hit a lot of monsters and left another man behind...\"",
    "volume": 40
  },
  {
    "type": "speech",
    "speaker": [ "FoxmonImperialReaper" ],
    "sound": "\"...We ID'd his bones after that.\"",
    "volume": 40
  },
  {
    "type": "speech",
    "speaker": [ "FoxmonImperialReaper" ],
    "sound": "\"...He was burnt to a crisp.\"",
    "volume": 40
  },
  {
    "type": "speech",
    "speaker": [ "FoxmonImperialReaper" ],
    "sound": "\"...That was before we saw the shadow monster.\"",
    "volume": 40
  },
  {
    "type": "speech",
    "speaker": [ "FoxmonImperialReaper" ],
    "sound": "\"A dropbear took out the sergeant...\"",
    "volume": 40
  },
  {
    "type": "speech",
    "speaker": [ "FoxmonImperialReaper" ],
    "sound": "\"...We buried him under a fruit tree.\"",
    "volume": 40
  },
  {
    "type": "speech",
    "speaker": [ "FoxmonImperialReaper" ],
    "sound": "\"Patrolling the swamps wasn't as shrimple as we thought...\"",
    "volume": 40
  },
  {
    "type": "speech",
    "speaker": [ "FoxmonImperialReaper" ],
    "sound": "\"...He had the maps, we ran around confused after.\"",
    "volume": 40
  },
  {
    "type": "speech",
    "speaker": [ "FoxmonImperialReaperRadio" ],
    "sound": "\"Reporting enemy combatants sighted!\"",
    "volume": 40
  },
  {
    "type": "speech",
    "speaker": [ "FoxmonImperialReaperRadio" ],
    "sound": "\"Reporting enemy activity!\"",
    "volume": 40
  },
  {
    "type": "speech",
    "speaker": [ "FoxmonImperialReaperRadio", "FoxmonImperialReaperSergeant" ],
    "sound": "\"Hostile sighted!\"",
    "volume": 40
  },
  {
    "type": "speech",
    "speaker": [ "FoxmonImperialReaperRadio", "FoxmonImperialReaperSergeant" ],
    "sound": "\"Under fire from insurgents!\"",
    "volume": 40
  },
  {
    "type": "speech",
    "speaker": [ "FoxmonImperialReaperRadio", "FoxmonImperialReaperSergeant" ],
    "sound": "\"Taking fire!\"",
    "volume": 40
  },
  {
    "type": "speech",
    "speaker": [ "FoxmonImperialReaperSergeant" ],
    "sound": "\"Radio! Engaging hostiles! Report in!\"",
    "volume": 40
  },
  {
    "type": "speech",
    "speaker": [ "FoxmonImperialReaperSergeant" ],
    "sound": "\"Radio! Report Status!\"",
    "volume": 40
  },
  {
    "type": "speech",
    "speaker": [ "FoxmonImperialReaperSergeant", "FoxmonImperialReaperRadio" ],
    "sound": "\"Enemy sighted!\"",
    "volume": 40
  },
  {
    "type": "speech",
    "speaker": [ "FoxmonImperialReaperSergeant" ],
    "sound": "\"On your feet, and go go go!\"",
    "volume": 40
  },
  {
    "type": "speech",
    "speaker": [ "FoxmonImperialReaperSergeant" ],
    "sound": "\"We've got hostiles!\"",
    "volume": 40
  },
  {
    "type": "speech",
    "speaker": [ "FoxmonImperialArbiter" ],
    "sound": "\"How did you get here?\"",
    "volume": 60
  },
  {
    "type": "speech",
    "speaker": [ "FoxmonImperialArbiter" ],
    "sound": "\"Hang on, some asshole broke in. I'll call you back.\"",
    "volume": 60
  },
  {
    "type": "speech",
    "speaker": [ "FoxmonImperialArbiter" ],
    "sound": "\"I'd love to come over, but I have work to do.\"",
    "volume": 40
  },
  {
    "type": "speech",
    "speaker": [ "FoxmonImperialArbiter" ],
    "sound": "\"You're about to have an accident.\"",
    "volume": 60
  },
  {
    "type": "speech",
    "speaker": [ "FoxmonImperialArbiter" ],
    "sound": "\"Know how I made captain? I smashed a rebel's skull in with a rock out of anger.\"",
    "volume": 60
  },
  {
    "type": "speech",
    "speaker": [ "FoxmonImperialArbiter" ],
    "sound": "\"Let's get wasted tomorrow, yeah I can't right now some work just showed up on my desk.\"",
    "volume": 40
  },
  {
    "type": "speech",
    "speaker": [ "FoxmonImperialArbiter" ],
    "sound": "\"Glad you could make it.\"",
    "volume": 60
  },
  {
    "type": "speech",
    "speaker": [ "FoxmonImperialArbiter" ],
    "sound": "\"Coffee, tea, or milk before I shoot you?\"",
    "volume": 60
  },
  {
    "type": "speech",
    "speaker": [ "FoxmonImperialArbiter" ],
    "sound": "\"Let's see how you like being deep fried.\"",
    "volume": 60
  },
  {
    "type": "speech",
    "speaker": [ "FoxmonImperialArbiter" ],
    "sound": "\"You unbelieveable prick, you actually broke in? I was having my lunch.\"",
    "volume": 60
  },
  {
    "type": "speech",
    "speaker": [ "FoxmonImperialArbiter" ],
    "sound": "\"Garbage day, motherfucker.\"",
    "volume": 60
  },
  {
    "type": "speech",
    "speaker": [ "FoxmonImperialArbiter" ],
    "sound": "\"Sorry, but now I've got to dump you in the deep fryer. WHERE YOU GOIN'?\"",
    "volume": 60
  },
  {
    "type": "speech",
    "speaker": [ "FoxmonImperialArbiter" ],
    "sound": "\"I'm about to beat the shit out of this guy. This rebel doesn't know.\"",
    "volume": 60
  },
  {
    "type": "speech",
    "speaker": [ "FoxmonImperialArbiter" ],
    "sound": "\"PUT THIS IN THE FUCKING OBITUARY!\"",
    "volume": 80
  },
  {
    "type": "speech",
    "speaker": [ "FoxmonImperialArbiter" ],
    "sound": "\"I'm going to sell your shoes after I kill you, jackass.\"",
    "volume": 60
  },
  {
    "type": "speech",
    "speaker": [ "FoxmonImperialArbiter" ],
    "sound": "\"We can wait jackass, we can wait.\"",
    "volume": 60
  },
  {
    "type": "speech",
    "speaker": [ "FoxmonImperialArbiter" ],
    "sound": "\"Fuck you. Fine, let's end this.\"",
    "volume": 60
  },
  {
    "type": "speech",
    "speaker": [ "FoxmonImperialArbiter" ],
    "sound": "\"Seeing you here is truly God spitting in my eye.\"",
    "volume": 60
  },
  {
    "type": "speech",
    "speaker": [ "FoxmonImperialArbiter" ],
    "sound": "\"I'm gonna finish this tea and them I'm going over there to kick your ass.\"",
    "volume": 60
  },
  {
    "type": "speech",
    "speaker": [ "FoxmonImperialArbiter" ],
    "sound": "\"I WILL CAN OPEN YOUR SKULL!\"",
    "volume": 80
  },
  {
    "type": "speech",
    "speaker": [ "FoxmonImperialArbiter" ],
    "sound": "\"I've seen swamp crabs more dangerous than you!\"",
    "volume": 60
  },
  {
    "type": "speech",
    "speaker": [ "FoxmonImperialArbiter" ],
    "sound": "\"A rebel? How did a rebel get on this base? I'll have somebody's ass for dinner!\"",
    "volume": 60
  },
  {
    "type": "speech",
    "speaker": [ "FoxmonImperialArbiter" ],
    "sound": "\"You call yourself a soldier?\"",
    "volume": 60
  },
  {
    "type": "speech",
    "speaker": [ "FoxmonImperialArbiter" ],
    "sound": "\"It's almost too easy.\"",
    "volume": 60
  },
  {
    "type": "speech",
    "speaker": [ "FoxmonImperialArbiter" ],
    "sound": "\"Hahaha. Your powers are no match for me, child.\"",
    "volume": 60
  },
  {
    "type": "speech",
    "speaker": [ "FoxmonImperialArbiter" ],
    "sound": "\"You should've picked an easier opponent.\"",
    "volume": 60
  },
  {
    "type": "speech",
    "speaker": [ "FoxmonImperialArbiter" ],
    "sound": "\"Die free in the rebellion, scum.\"",
    "volume": 60
  },
  {
    "type": "speech",
    "speaker": [ "FoxmonImperialArbiter" ],
    "sound": "\"I want those rebels dead!\"",
    "volume": 60
  },
  {
    "type": "speech",
    "speaker": [ "FoxmonImperialGolemSergeant" ],
    "sound": "\"You better start running, asshole!\"",
    "volume": 60
  },
  {
    "type": "speech",
    "speaker": [ "FoxmonImperialGolemSergeant" ],
    "sound": "\"I'm breaking your legs!\"",
    "volume": 60
  },
  {
    "type": "speech",
    "speaker": [ "FoxmonImperialGolemSergeant" ],
    "sound": "\"Get over here!\"",
    "volume": 60
  },
  { 
    "type": "speech",
    "speaker": [ "FoxmonImperialGolemSergeant" ],
    "sound": "\"I suppose if you're very lucky you could give me a headache with a rifle.\"",
    "volume": 60
  },
  {
    "type": "speech",
    "speaker": [ "FoxmonImperialGolemSergeant" ],
    "sound": "\"I'm the man! I AM THE MAN!\"",
    "volume": 90
  },
  {
    "type": "speech",
    "speaker": [ "FoxmonImperialGolemSergeant" ],
    "sound": "\"Why's everything so tame? I like my life insane!\"",
    "volume": 60
  },
  {
    "type": "speech",
    "speaker": [ "FoxmonImperialGolemSergeant" ],
    "sound": "\"Right now! Can't find a way to get across the hate when I see you!\"",
    "volume": 60
  },
  {
    "type": "speech",
    "speaker": [ "FoxmonImperialReaper" ],
    "sound": "humming.",
    "volume": 30
  },
  {
    "type": "speech",
    "speaker": [ "FoxmonImperialReaper" ],
    "sound": "whistling.",
    "volume": 30
  },
  {
    "type": "speech",
    "speaker": [ "FoxmonImperialReaper" ],
    "sound": "lyrics from a rock song.",
    "volume": 40
  },
  {
    "type": "speech",
    "speaker": [ "FoxmonImperialReaper" ],
    "sound": "lyrics from a metal song.",
    "volume": 40
  },
  {
    "type": "speech",
    "speaker": [ "FoxmonImperialReaper" ],
    "sound": "lyrics from a pop song.",
    "volume": 40
  },
  {
    "type": "speech",
    "speaker": [ "FoxmonImperialReaper" ],
    "sound": "lyrics from a childrens rhyme.",
    "volume": 40
  },
  {
    "type": "speech",
    "speaker": [ "FoxmonImperialReaper" ],
    "sound": "lyrics from a rap song.",
    "volume": 40
  },
  {
    "type": "speech",
    "speaker": [ "FoxmonImperialReaper" ],
    "sound": "lyrics from a country song.",
    "volume": 40
  },
  {
    "type": "speech",
    "speaker": [ "FoxmonImperialReaper" ],
    "sound": "lyrics from an Imperial song.",
    "volume": 40
  },
  {
    "type": "speech",
    "speaker": [ "FoxmonImperialReaper" ],
    "sound": "lyrics from JPop.",
    "volume": 40
  },
  {
    "type": "speech",
    "speaker": [ "FoxmonImperialReaper" ],
    "sound": "lyrics from KPop.",
    "volume": 40
  },
  {
    "type": "speech",
    "speaker": [ "FoxmonImperialReaper" ],
    "sound": "lyrics from a Russian song.",
    "volume": 40
  },
  {
    "type": "speech",
    "speaker": [ "FoxmonImperialReaper" ],
    "sound": "lyrics from a German song.",
    "volume": 40
  },
  {
    "type": "speech",
    "speaker": [ "FoxmonImperialReaper" ],
    "sound": "lyrics from a Spanish song.",
    "volume": 40
  },
  {
    "type": "speech",
    "speaker": [ "FoxmonImperialReaper" ],
    "sound": "lyrics from a French song.",
    "volume": 40
  },
  {
    "type": "speech",
    "speaker": [ "FoxmonImperialReaper" ],
    "sound": "lyrics from a chinese song.",
    "volume": 40
  },
  {
    "type": "speech",
    "speaker": [ "FoxmonImperialReaper" ],
    "sound": "lyrics from a song in a language you don't recognize.",
    "volume": 40
  },
  {
    "type": "speech",
    "speaker": [ "FoxmonImperialReaper" ],
    "sound": "lyrics from Mariya Takeuchi - Plastic Love.",
    "volume": 40
  },
  {
    "type": "speech",
    "speaker": [ "FoxmonImperialReaper" ],
    "sound": "lyrics from Kaskad - Alarm Again.",
    "volume": 40
  },
  {
    "type": "speech",
    "speaker": [ "FoxmonImperialReaper" ],
    "sound": "lyrics from Kaskad - Live on, Soviets.",
    "volume": 40
  },
  {
    "type": "speech",
    "speaker": [ "FoxmonImperialReaper" ],
    "sound": "lyrics from Kaskad - Kukushka.",
    "volume": 40
  },
  {
    "type": "speech",
    "speaker": [ "FoxmonImperialReaper" ],
    "sound": "lyrics from Kaskad - BTR.",
    "volume": 40
  },
  {
    "type": "speech",
    "speaker": [ "FoxmonImperialReaper" ],
    "sound": "lyrics from Kaskad - We are leaving.",
    "volume": 40
  },
  {
    "type": "speech",
    "speaker": [ "FoxmonImperialReaper" ],
    "sound": "lyrics from Don't tell mom I'm in Chechnya.",
    "volume": 40
  },
  {
    "type": "speech",
    "speaker": [ "FoxmonImperialReaper" ],
    "sound": "lyrics from My Yard - Three choppers over Mozdok.",
    "volume": 40
  },
  {
    "type": "speech",
    "speaker": [ "FoxmonImperialReaper" ],
    "sound": "lyrics from Nikolai Emelin - Hold on, brother.",
    "volume": 40
  },
  {
    "type": "speech",
    "speaker": [ "FoxmonImperialReaper" ],
    "sound": "lyrics from Lubeh - Davai Za.",
    "volume": 40
  },
  {
    "type": "speech",
    "speaker": [ "FoxmonImperialReaper" ],
    "sound": "lyrics from Lubeh - Kombat.",
    "volume": 40
  },
  {
    "type": "speech",
    "speaker": [ "FoxmonImperialReaper" ],
    "sound": "\"It ain't me, I ain't no fortunate one.\"",
    "volume": 40
  },
  {
    "type": "speech",
    "speaker": [ "FoxmonImperialReaper" ],
    "sound": "\"Welcome to the jungle, we've got fun and games.\"",
    "volume": 40
  },
  {
    "type": "speech",
    "speaker": [ "FoxmonImperialReaper" ],
    "sound": "\"We are the people that can find, whatever you may need.\"",
    "volume": 40
  },
  {
    "type": "speech",
    "speaker": [ "FoxmonImperialReaper" ],
    "sound": "\"You only get one shot, do not miss your chance to blow.\"",
    "volume": 40
  },
  {
    "type": "speech",
    "speaker": [ "FoxmonImperialReaper" ],
    "sound": "\"But he won't give up that easy, no, he won't have it.\"",
    "volume": 40
  },
  {
    "type": "speech",
    "speaker": [ "FoxmonImperialReaper" ],
    "sound": "\"But I ain't never crossed a man who didn't deserve it.\"",
    "volume": 40
  },
  {
    "type": "speech",
    "speaker": [ "FoxmonImperialReaper" ],
    "sound": "\"It's not that hard to get away with murder, just start with stealing a kiss and take it further.\"",
    "volume": 40
  },
  {
    "type": "speech",
    "speaker": [ "FoxmonImperialReaper" ],
    "sound": "\"They are the panzer elite, born to compete, never retreat.\"",
    "volume": 40
  },
  {
    "type": "speech",
    "speaker": [ "FoxmonImperialReaper" ],
    "sound": "\"Pride of the nation, the beast made of steel, Bismarck in motion...\"",
    "volume": 40
  },
  {
    "type": "speech",
    "speaker": [ "FoxmonImperialReaper" ],
    "sound": "\"Then the winged Hussars arrived, coming down the mountainside.\"",
    "volume": 40
  },
  {
    "type": "speech",
    "speaker": [ "FoxmonImperialReaper" ],
    "sound": "\"You'll be stopped on the steps of our gate! On this field you're only facing our hate!\"",
    "volume": 40
  },
  {
    "type": "speech",
    "speaker": [ "FoxmonImperialReaper" ],
    "sound": "\"Come out ye black and tans, come out and fight me like a man.\"",
    "volume": 40
  },
  {
    "type": "speech",
    "speaker": [ "FoxmonImperialReaper" ],
    "sound": "\"Oh, we are the British army and we're here to take your land.\"",
    "volume": 40
  },
  {
    "type": "speech",
    "speaker": [ "FoxmonImperialReaper" ],
    "sound": "\"Country roads, take me home, to the place I belong...\"",
    "volume": 40
  },
  {
    "type": "speech",
    "speaker": [ "FoxmonImperialReaper" ],
    "sound": "\"All the other kids with their pumped up kicks you better run better run, outrun my gun.\"",
    "volume": 40
  },
  {
    "type": "speech",
    "speaker": [ "FoxmonImperialReaper" ],
    "sound": "\"We don't need no pentagram, we don't pray to God.\"",
    "volume": 40
  },
  {
    "type": "speech",
    "speaker": [ "FoxmonImperialReaper" ],
    "sound": "\"Banners up high, as we rise like a legion, sworn, all for the light we inverse.\"",
    "volume": 40
  },
  {
    "type": "speech",
    "speaker": [ "FoxmonImperialReaper" ],
    "sound": "\"Combat ahead, and the night calls for heroes. Ready for fire command.\"",
    "volume": 40
  },
  {
    "type": "speech",
    "speaker": [ "FoxmonImperialReaper" ],
    "sound": "\"Hit me baby one more time.\"",
    "volume": 40
  },
  {
    "type": "speech",
    "speaker": [ "FoxmonImperialReaper" ],
    "sound": "\"All that stubborn loyalty, is gonna get you killed in a world built on convenient theories.\"",
    "volume": 40
  },
  {
    "type": "speech",
    "speaker": [ "FoxmonImperialReaper" ],
    "sound": "\"If you're gonna control me, at least make it interesting theatrically.\"",
    "volume": 40
  },
  {
    "type": "speech",
    "speaker": [ "FoxmonImperialReaper" ],
    "sound": "\"Now, it's time for another vendetta.\"",
    "volume": 40
  },
  {
    "type": "speech",
    "speaker": [ "FoxmonImperialReaper" ],
    "sound": "\"Children of the city, see only the neon stars reflected upon the murky gutter sky.\"",
    "volume": 40
  },
  {
    "type": "speech",
    "speaker": [ "FoxmonImperialReaper" ],
    "sound": "\"I am fire, burn those who dare to care for me.\"",
    "volume": 40
  },
  {
    "type": "speech",
    "speaker": [ "FoxmonImperialReaper" ],
    "sound": "\"For you, angels have fallen and now they're gone. See now they're gone.\"",
    "volume": 40
  },
  {
    "type": "speech",
    "speaker": [ "FoxmonImperialReaper" ],
    "sound": "\"So I have a reason, reason to see you dead.\"",
    "volume": 40
  },
  {
    "type": "speech",
    "speaker": [ "FoxmonImperialReaper" ],
    "sound": "\"I walked down a path, leading to the past.\"",
    "volume": 40
  },
  {
    "type": "speech",
    "speaker": [ "FoxmonImperialReaper" ],
    "sound": "\"Lament, if you wanted me to live, if you want me to forgive, if you want us to pretend like we're civilized humans.\"",
    "volume": 40
  },
  {
    "type": "speech",
    "speaker": [ "FoxmonImperialReaper" ],
    "sound": "\"Tell me why, tell me why, tell me why, a malfunction, only this time I'm smiling at your side.\"",
    "volume": 40
  },
  {
    "type": "speech",
    "speaker": [ "FoxmonImperialGolem" ],
    "sound": "loud music from a speaker, you don't know the song.",
    "volume": 120
  },
  {
    "type": "speech",
    "speaker": [ "FoxmonImperialGolem" ],
    "sound": "loud music from a speaker, its Doom E1M1.",
    "volume": 120
  },
  {
    "type": "speech",
    "speaker": [ "FoxmonImperialGolem" ],
    "sound": "loud music from a speaker, its heavy metal.",
    "volume": 120
  },
  {
    "type": "speech",
    "speaker": [ "FoxmonImperialGolem" ],
    "sound": "loud music from a speaker, its Slayer.",
    "volume": 120
  },
  {
    "type": "speech",
    "speaker": [ "FoxmonImperialGolem" ],
    "sound": "loud music from a speaker, its Slipknot.",
    "volume": 120
  },
  {
    "type": "speech",
    "speaker": [ "FoxmonImperialGolem" ],
    "sound": "loud music from a speaker, its Metallica.",
    "volume": 120
  },
  {
    "type": "speech",
    "speaker": [ "FoxmonImperialGolem" ],
    "sound": "loud music from a speaker, its Blue Oyster Cult.",
    "volume": 120
  },
  {
    "type": "speech",
    "speaker": [ "FoxmonImperialGolem" ],
    "sound": "loud music from a speaker, its Rolling Stones.",
    "volume": 120
  },
  {
    "type": "speech",
    "speaker": [ "FoxmonImperialGolem" ],
    "sound": "loud music from a speaker, its Metallica.",
    "volume": 120
  },
  {
    "type": "speech",
    "speaker": [ "FoxmonImperialGolem" ],
    "sound": "loud music from a speaker, its rap.",
    "volume": 120
  },
  {
    "type": "speech",
    "speaker": [ "FoxmonImperialGolem" ],
    "sound": "loud music from a speaker, its Eminem.",
    "volume": 120
  },
  {
    "type": "speech",
    "speaker": [ "FoxmonImperialGolem" ],
    "sound": "loud music from a speaker, its 50 cent.",
    "volume": 120
  },
  {
    "type": "speech",
    "speaker": [ "FoxmonImperialGolem" ],
    "sound": "loud music from a speaker, its rap.",
    "volume": 120
  },
  {
    "type": "speech",
    "speaker": [ "FoxmonImperialGolem" ],
    "sound": "loud music from a speaker, its rock and roll.",
    "volume": 120
  },
  {
    "type": "speech",
    "speaker": [ "FoxmonImperialGolem" ],
    "sound": "loud music from a speaker, its from Halo.",
    "volume": 120
  },
  {
    "type": "speech",
    "speaker": [ "FoxmonImperialGolem" ],
    "sound": "loud music from a speaker, its Winter Contingency Action from Reach.",
    "volume": 120
  },
  {
    "type": "speech",
    "speaker": [ "FoxmonImperialGolem" ],
    "sound": "loud music from a speaker, its from an FPS.",
    "volume": 120
  },
  {
    "type": "speech",
    "speaker": [ "FoxmonImperialGolem" ],
    "sound": "loud music from a speaker, its from an RTS.",
    "volume": 120
  },
  {
    "type": "speech",
    "speaker": [ "FoxmonImperialGolem" ],
    "sound": "loud music from a speaker, its from Tekken.",
    "volume": 120
  },
  {
    "type": "speech",
    "speaker": [ "FoxmonImperialGolem" ],
    "sound": "loud music from a speaker, its from the Yakuza series.",
    "volume": 120
  },
  {
    "type": "speech",
    "speaker": [ "FoxmonImperialGolem" ],
    "sound": "loud music from a speaker, its Yakuza 6 Kamuro again.",
    "volume": 120
  },
  {
    "type": "speech",
    "speaker": [ "FoxmonImperialGolem" ],
    "sound": "loud music from a speaker, its from Doom.",
    "volume": 120
  },
  {
    "type": "speech",
    "speaker": [ "FoxmonImperialGolem" ],
    "sound": "loud music from a speaker, its from C&C.",
    "volume": 120
  },
  {
    "type": "speech",
    "speaker": [ "FoxmonImperialGolem" ],
    "sound": "loud music from a speaker, its Red Alert 2 Hell March.",
    "volume": 120
  },
  {
    "type": "speech",
    "speaker": [ "FoxmonImperialGolem" ],
    "sound": "loud music from a speaker, its from a JRPG.",
    "volume": 120
  },
  {
    "type": "speech",
    "speaker": [ "FoxmonImperialGolem" ],
    "sound": "loud music from a speaker, its from Starcraft 2.",
    "volume": 120
  },
  {
    "type": "speech",
    "speaker": [ "FoxmonImperialGolem" ],
    "sound": "loud music from a speaker, its from Trails in the Sky.",
    "volume": 120
  },
  {
    "type": "speech",
    "speaker": [ "FoxmonImperialGolem" ],
    "sound": "loud music from a speaker, its from Trails to Azure.",
    "volume": 120
  },
  {
    "type": "speech",
    "speaker": [ "FoxmonImperialGolem" ],
    "sound": "loud music from a speaker, its from Mario.",
    "volume": 120
  },
  {
    "type": "speech",
    "speaker": [ "FoxmonImperialGolem" ],
    "sound": "loud music from a speaker, its from Zelda.",
    "volume": 120
  },
  {
    "type": "speech",
    "speaker": [ "FoxmonImperialGolem" ],
    "sound": "loud music from a speaker, ITS MALO MART FROM TWILIGHT PRINCESS!",
    "volume": 180
  }
]